LICENSE
MANIFEST.in
README.md
setup.py
histudio/__init__.py
histudio/cli.py
histudio/debug.py
histudio/event_stream.py
histudio/job_settings.py
histudio.egg-info/PKG-INFO
histudio.egg-info/SOURCES.txt
histudio.egg-info/dependency_links.txt
histudio.egg-info/entry_points.txt
histudio.egg-info/requires.txt
histudio.egg-info/top_level.txt
histudio/app/__init__.py
histudio/app/api.py
histudio/app/config.py
histudio/app/mixin.py
histudio/app/swagger.py
histudio/app/blueprints/__init__.py
histudio/app/blueprints/assets/__init__.py
histudio/app/blueprints/assets/resources.py
histudio/app/blueprints/auth/__init__.py
histudio/app/blueprints/auth/resources.py
histudio/app/blueprints/breakdown/__init__.py
histudio/app/blueprints/breakdown/resources.py
histudio/app/blueprints/comments/__init__.py
histudio/app/blueprints/comments/resources.py
histudio/app/blueprints/crud/__init__.py
histudio/app/blueprints/crud/asset_instance.py
histudio/app/blueprints/crud/attachment_file.py
histudio/app/blueprints/crud/base.py
histudio/app/blueprints/crud/comments.py
histudio/app/blueprints/crud/custom_action.py
histudio/app/blueprints/crud/day_off.py
histudio/app/blueprints/crud/department.py
histudio/app/blueprints/crud/entity.py
histudio/app/blueprints/crud/entity_link.py
histudio/app/blueprints/crud/entity_type.py
histudio/app/blueprints/crud/event.py
histudio/app/blueprints/crud/file_status.py
histudio/app/blueprints/crud/metadata_descriptor.py
histudio/app/blueprints/crud/milestone.py
histudio/app/blueprints/crud/news.py
histudio/app/blueprints/crud/notification.py
histudio/app/blueprints/crud/organisation.py
histudio/app/blueprints/crud/output_file.py
histudio/app/blueprints/crud/output_type.py
histudio/app/blueprints/crud/person.py
histudio/app/blueprints/crud/playlist.py
histudio/app/blueprints/crud/preview_background_file.py
histudio/app/blueprints/crud/preview_file.py
histudio/app/blueprints/crud/project.py
histudio/app/blueprints/crud/project_status.py
histudio/app/blueprints/crud/schedule_item.py
histudio/app/blueprints/crud/search_filter.py
histudio/app/blueprints/crud/search_filter_group.py
histudio/app/blueprints/crud/software.py
